{
  "indexes": [
    {
      "collectionGroup": "testResults",
      "queryScope": "COLLECTION",
      "fields": [
        {
          "fieldPath": "userId",
          "order": "ASCENDING"
        },
        {
          "fieldPath": "createdAt",
          "order": "DESCENDING"
        }
      ]
    },
    {
      "collectionGroup": "users",
      "queryScope": "COLLECTION",
      "fields": [
        {
          "fieldPath": "role",
          "order": "ASCENDING"
        },
        {
          "fieldPath": "totalDaysPracticed",
          "order": "DESCENDING"
        }
      ]
    }
  ],
  "fieldOverrides": []
}